mono/__init__.py
mono/finetuning.py
mono/main.py
mono/processing.py
mono/vectordb.py
mono_kit-0.1.4.dist-info/METADATA
mono_kit-0.1.4.dist-info/WHEEL
mono_kit-0.1.4.dist-info/top_level.txt
mono_kit-0.1.4.dist-info/RECORD
