Metadata-Version: 2.4
Name: mono-kit
Version: 0.1.4
Summary: ML toolkit for developers to build document, audio, and image similarity retrieval systems with pretrained and finetunable models—ready to use out of the box.
Requires-Dist: chromadb==1.0.13
Requires-Dist: librosa==0.11.0
Requires-Dist: tensorflow_hub==0.16.1
Requires-Dist: tensorflow==2.19.0
Requires-Dist: semantic_text_splitter==0.27.0
Requires-Dist: numpy==2.1.3
Requires-Dist: Pillow==11.2.1
Dynamic: description
Dynamic: description-content-type
Dynamic: requires-dist
Dynamic: summary
